{
  "pets": [
    {
      "id": 1,
      "name": "Bella",
      "status": "In Danger",
      "lat": 40.776676,
      "lng": -73.971321,
      "description": "Owner reports Bella is trapped in apartment at 123 W 72nd St."
    },
    {
      "id": 2,
      "name": "Max",
      "status": "In Danger",
      "lat": 40.79224,
      "lng": -73.973553,
      "description": "Max is in a 5th floor unit at 250 W 94th St, owner unable to return."
    },
    {
      "id": 3,
      "name": "Luna",
      "status": "In Danger",
      "lat": 40.744,
      "lng": -73.9956,
      "description": "Rabbit seen on balcony at 460 W 23rd St, fire evacuation zone."
    },
    {
      "id": 4,
      "name": "Charlie",
      "status": "Rescued",
      "lat": 40.748817,
      "lng": -73.985428,
      "description": "Golden retriever rescued from building rooftop."
    },
    {
      "id": 5,
      "name": "Milo",
      "status": "Rescued",
      "lat": 40.7527,
      "lng": -73.9772,
      "description": "Gray kitten safely recovered by FDNY, currently at ACC in Yorkville."
    },
    {
      "id": 6,
      "name": "Sadie",
      "status": "Rescued",
      "lat": 40.7549,
      "lng": -73.984,
      "description": "Parrot returned to owner in Midtown."
    },
    {
      "id": 7,
      "name": "Rocky",
      "status": "Missing",
      "lat": 40.73061,
      "lng": -73.935242,
      "description": "Lost beagle last seen in East Village."
    },
    {
      "id": 8,
      "name": "Zoe",
      "status": "Missing",
      "lat": 40.7282,
      "lng": -73.7949,
      "description": "Cockatiel escaped during storm in Queens."
    },
    {
      "id": 9,
      "name": "Chloe",
      "status": "Missing",
      "lat": 40.742054,
      "lng": -74.004821,
      "description": "Calico cat ran out during evacuation."
    }
  ]
}